WrdSmth/__init__.py
WrdSmth/cleaning.py
WrdSmth/initialization.py
WrdSmth/lemmatization.py
WrdSmth/stemming.py
WrdSmth/tokenization.py
WrdSmth/vectorization.py
WrdSmth-0.1.6.dist-info/METADATA
WrdSmth-0.1.6.dist-info/WHEEL
WrdSmth-0.1.6.dist-info/top_level.txt
WrdSmth-0.1.6.dist-info/RECORD
