Metadata-Version: 2.1
Name: WrdSmth
Version: 0.1.6
Summary: Your Python Text Preprocessing Toolkit
Author: Nazaryan Artem Karapetovich
Author-email: spanishiwasc2@gmail.com
Classifier: Development Status :: 3 - Alpha
Classifier: Intended Audience :: Developers
Classifier: License :: OSI Approved :: MIT License
Classifier: Programming Language :: Python :: 3
Classifier: Programming Language :: Python :: 3.6
Classifier: Programming Language :: Python :: 3.7
Classifier: Programming Language :: Python :: 3.8
Classifier: Programming Language :: Python :: 3.9
Classifier: Programming Language :: Python :: 3.10
Classifier: Programming Language :: Python :: 3.11
Classifier: Programming Language :: Python :: 3.12
Requires-Dist: nltk
Requires-Dist: numba
Requires-Dist: spacy
Requires-Dist: langdetect
Requires-Dist: scikit-learn
